badcode_utilities/__init__.py
badcode_utilities/badwords.txt
badcode_utilities/main.py
badcode_utilities-0.6.dist-info/LICENSE
badcode_utilities-0.6.dist-info/METADATA
badcode_utilities-0.6.dist-info/WHEEL
badcode_utilities-0.6.dist-info/top_level.txt
badcode_utilities-0.6.dist-info/RECORD
