Metadata-Version: 2.1
Name: badcode-utilities
Version: 0.6
Summary: A collection of utility functions for string handling and filtering.
Home-page: UNKNOWN
License: UNKNOWN
Platform: UNKNOWN
License-File: LICENSE
